{
  "segment_metadata": {
    "segment_number": "181",
    "segment_filename": "181_bible_ancient-greek.txt",
    "text_identification": "This appears to be from the New Testament, likely from the Johannine epistles (1 John and 2 John). The language and themes align with the writings attributed to the Apostle John.",
    "text_summary": "This segment emphasizes the importance of belief in Jesus Christ, the Son of God, for attaining eternal life. It highlights that having the Son means having life, and rejecting Him equates to rejecting God's testimony. The passage also discusses the assurance believers have in prayer, the distinction between sins leading to death and those that do not, and the protection believers receive from the evil one. It affirms that believers are of God, while the world lies in wickedness. The Son of God has come to give understanding so that we may know the true God. The text concludes with a warning against idolatry and greetings from the Elder to a chosen lady and her children, emphasizing love, truth, grace, mercy, and peace. It stresses the importance of walking in truth and obeying God's commandments, while also cautioning against deceivers who deny Jesus Christ."
  },
  "topic_analysis": [
    {
      "topic": "Belief in Jesus Christ and Eternal Life",
      "sentiment_polarity": {
        "score": 0.9,
        "confidence": 95,
        "reasoning": "The passage directly links belief in Jesus to eternal life, a concept with overwhelmingly positive connotations in Christian theology."
      },
      "emotions": {
        "Joy": {
          "weight": 0.8,
          "confidence": 90,
          "reasoning": "Eternal life is presented as a source of immense joy and fulfillment."
        },
        "Trust": {
          "weight": 0.9,
          "confidence": 95,
          "reasoning": "Belief in Jesus necessitates a high degree of trust in God's promises."
        },
        "Fear": {
          "weight": 0.1,
          "confidence": 70,
          "reasoning": "There's a subtle fear of missing out on eternal life if one doesn't believe."
        },
        "Surprise": {
          "weight": 0.2,
          "confidence": 60,
          "reasoning": "The gift of eternal life can be seen as a surprising act of grace."
        },
        "Sadness": {
          "weight": 0.1,
          "confidence": 70,
          "reasoning": "The alternative to belief is a state of spiritual death, which carries sadness."
        },
        "Disgust": {
          "weight": 0.0,
          "confidence": 80,
          "reasoning": "No disgust is explicitly present in this concept."
        },
        "Anger": {
          "weight": 0.0,
          "confidence": 80,
          "reasoning": "No anger is explicitly present in this concept."
        },
        "Anticipation": {
          "weight": 0.7,
          "confidence": 85,
          "reasoning": "The promise of eternal life creates a strong sense of anticipation."
        }
      }
    },
    {
      "topic": "Assurance in Prayer",
      "sentiment_polarity": {
        "score": 0.8,
        "confidence": 90,
        "reasoning": "The passage speaks of God hearing and answering prayers that align with His will, which is a comforting and positive concept for believers."
      },
      "emotions": {
        "Joy": {
          "weight": 0.6,
          "confidence": 80,
          "reasoning": "Receiving answers to prayer brings joy."
        },
        "Trust": {
          "weight": 0.9,
          "confidence": 95,
          "reasoning": "Prayer is based on trust in God's willingness to listen and act."
        },
        "Fear": {
          "weight": 0.1,
          "confidence": 70,
          "reasoning": "There's a slight fear that prayers might not be answered if they are not according to God's will."
        },
        "Surprise": {
          "weight": 0.3,
          "confidence": 60,
          "reasoning": "Unexpected answers to prayer can be surprising."
        },
        "Sadness": {
          "weight": 0.1,
          "confidence": 70,
          "reasoning": "Unanswered prayer can bring sadness."
        },
        "Disgust": {
          "weight": 0.0,
          "confidence": 80,
          "reasoning": "No disgust is explicitly present in this concept."
        },
        "Anger": {
          "weight": 0.0,
          "confidence": 80,
          "reasoning": "No anger is explicitly present in this concept."
        },
        "Anticipation": {
          "weight": 0.8,
          "confidence": 90,
          "reasoning": "Prayer involves anticipation of God's response."
        }
      }
    },
    {
      "topic": "Sin and Death",
      "sentiment_polarity": {
        "score": -0.3,
        "confidence": 85,
        "reasoning": "The discussion of sin and its consequences, including the distinction between sins leading to death and those that do not, introduces a complex and potentially negative element. However, the passage also offers hope for forgiveness and restoration."
      },
      "emotions": {
        "Joy": {
          "weight": 0.1,
          "confidence": 60,
          "reasoning": "The possibility of forgiveness tempers the negativity."
        },
        "Trust": {
          "weight": 0.3,
          "confidence": 70,
          "reasoning": "Trust in God's mercy is implied."
        },
        "Fear": {
          "weight": 0.8,
          "confidence": 90,
          "reasoning": "The concept of sin leading to death evokes fear."
        },
        "Surprise": {
          "weight": 0.2,
          "confidence": 60,
          "reasoning": "The specific consequences of different sins might be surprising."
        },
        "Sadness": {
          "weight": 0.7,
          "confidence": 85,
          "reasoning": "Sin and death are inherently sad topics."
        },
        "Disgust": {
          "weight": 0.4,
          "confidence": 75,
          "reasoning": "Sin can be seen as something morally disgusting."
        },
        "Anger": {
          "weight": 0.3,
          "confidence": 70,
          "reasoning": "Sin can provoke anger, both at oneself and at the forces of evil."
        },
        "Anticipation": {
          "weight": 0.3,
          "confidence": 70,
          "reasoning": "There's anticipation of judgment or forgiveness."
        }
      }
    },
    {
      "topic": "Protection from the Evil One",
      "sentiment_polarity": {
        "score": 0.7,
        "confidence": 85,
        "reasoning": "The assurance that those born of God are protected from the evil one is a positive and comforting message."
      },
      "emotions": {
        "Joy": {
          "weight": 0.4,
          "confidence": 70,
          "reasoning": "The protection brings a sense of joy and security."
        },
        "Trust": {
          "weight": 0.8,
          "confidence": 90,
          "reasoning": "It requires trust in God's power to protect."
        },
        "Fear": {
          "weight": 0.3,
          "confidence": 75,
          "reasoning": "The existence of the evil one implies a potential for fear."
        },
        "Surprise": {
          "weight": 0.1,
          "confidence": 60,
          "reasoning": "The nature of God's protection might be surprising at times."
        },
        "Sadness": {
          "weight": 0.1,
          "confidence": 60,
          "reasoning": "The existence of evil is a source of sadness."
        },
        "Disgust": {
          "weight": 0.5,
          "confidence": 80,
          "reasoning": "The evil one is a figure of moral disgust."
        },
        "Anger": {
          "weight": 0.4,
          "confidence": 75,
          "reasoning": "The evil one provokes anger and opposition."
        },
        "Anticipation": {
          "weight": 0.5,
          "confidence": 70,
          "reasoning": "There's anticipation of continued protection."
        }
      }
    },
    {
      "topic": "Knowing the True God",
      "sentiment_polarity": {
        "score": 0.9,
        "confidence": 95,
        "reasoning": "The statement that the Son of God has come to give understanding so that we may know the true God is profoundly positive."
      },
      "emotions": {
        "Joy": {
          "weight": 0.8,
          "confidence": 90,
          "reasoning": "Knowing the true God brings immense joy."
        },
        "Trust": {
          "weight": 0.9,
          "confidence": 95,
          "reasoning": "It requires trust in Jesus as the revealer of God."
        },
        "Fear": {
          "weight": 0.1,
          "confidence": 60,
          "reasoning": "The possibility of being deceived is a subtle fear."
        },
        "Surprise": {
          "weight": 0.3,
          "confidence": 70,
          "reasoning": "The nature of God's revelation might be surprising."
        },
        "Sadness": {
          "weight": 0.1,
          "confidence": 60,
          "reasoning": "Ignorance of God is a source of sadness."
        },
        "Disgust": {
          "weight": 0.0,
          "confidence": 80,
          "reasoning": "No disgust is explicitly present in this concept."
        },
        "Anger": {
          "weight": 0.0,
          "confidence": 80,
          "reasoning": "No anger is explicitly present in this concept."
        },
        "Anticipation": {
          "weight": 0.8,
          "confidence": 90,
          "reasoning": "There's anticipation of deeper understanding."
        }
      }
    },
    {
      "topic": "Warning Against Idolatry",
      "sentiment_polarity": {
        "score": -0.5,
        "confidence": 80,
        "reasoning": "A warning against idolatry carries a negative connotation, as it implies a deviation from true worship."
      },
      "emotions": {
        "Joy": {
          "weight": 0.1,
          "confidence": 60,
          "reasoning": "There's a subtle joy in remaining faithful."
        },
        "Trust": {
          "weight": 0.3,
          "confidence": 70,
          "reasoning": "It requires trust in God's commands."
        },
        "Fear": {
          "weight": 0.7,
          "confidence": 85,
          "reasoning": "The consequences of idolatry evoke fear."
        },
        "Surprise": {
          "weight": 0.2,
          "confidence": 60,
          "reasoning": "The deceptive nature of idols might be surprising."
        },
        "Sadness": {
          "weight": 0.6,
          "confidence": 80,
          "reasoning": "Idolatry is a source of sadness and spiritual loss."
        },
        "Disgust": {
          "weight": 0.7,
          "confidence": 85,
          "reasoning": "Idolatry is a morally disgusting practice."
        },
        "Anger": {
          "weight": 0.5,
          "confidence": 75,
          "reasoning": "Idolatry provokes anger at the deception and false worship."
        },
        "Anticipation": {
          "weight": 0.2,
          "confidence": 60,
          "reasoning": "There's anticipation of judgment or consequences."
        }
      }
    },
    {
      "topic": "Love and Truth",
      "sentiment_polarity": {
        "score": 0.9,
        "confidence": 95,
        "reasoning": "The emphasis on love and truth is overwhelmingly positive, as these are core values in Christian ethics."
      },
      "emotions": {
        "Joy": {
          "weight": 0.9,
          "confidence": 95,
          "reasoning": "Love and truth are sources of immense joy."
        },
        "Trust": {
          "weight": 0.9,
          "confidence": 95,
          "reasoning": "They are based on trust and faithfulness."
        },
        "Fear": {
          "weight": 0.1,
          "confidence": 60,
          "reasoning": "The absence of love and truth evokes fear."
        },
        "Surprise": {
          "weight": 0.1,
          "confidence": 60,
          "reasoning": "The depth of God's love might be surprising."
        },
        "Sadness": {
          "weight": 0.1,
          "confidence": 60,
          "reasoning": "The lack of love and truth is a source of sadness."
        },
        "Disgust": {
          "weight": 0.0,
          "confidence": 80,
          "reasoning": "No disgust is explicitly present in this concept."
        },
        "Anger": {
          "weight": 0.0,
          "confidence": 80,
          "reasoning": "No anger is explicitly present in this concept."
        },
        "Anticipation": {
          "weight": 0.9,
          "confidence": 95,
          "reasoning": "There's anticipation of continued love and truth."
        }
      }
    },
    {
      "topic": "Obeying God's Commandments",
      "sentiment_polarity": {
        "score": 0.7,
        "confidence": 90,
        "reasoning": "Obeying God's commandments is presented as a positive and necessary aspect of Christian life."
      },
      "emotions": {
        "Joy": {
          "weight": 0.6,
          "confidence": 80,
          "reasoning": "Obedience brings a sense of joy and fulfillment."
        },
        "Trust": {
          "weight": 0.8,
          "confidence": 90,
          "reasoning": "It requires trust in God's wisdom and authority."
        },
        "Fear": {
          "weight": 0.4,
          "confidence": 75,
          "reasoning": "The consequences of disobedience evoke fear."
        },
        "Surprise": {
          "weight": 0.1,
          "confidence": 60,
          "reasoning": "The specific requirements of God's commandments might be surprising."
        },
        "Sadness": {
          "weight": 0.3,
          "confidence": 70,
          "reasoning": "Disobedience leads to sadness and regret."
        },
        "Disgust": {
          "weight": 0.2,
          "confidence": 65,
          "reasoning": "Disobedience can be seen as morally wrong."
        },
        "Anger": {
          "weight": 0.1,
          "confidence": 60,
          "reasoning": "Disobedience might provoke anger at oneself."
        },
        "Anticipation": {
          "weight": 0.7,
          "confidence": 85,
          "reasoning": "There's anticipation of blessings for obedience."
        }
      }
    },
    {
      "topic": "Deceivers and False Teachings",
      "sentiment_polarity": {
        "score": -0.6,
        "confidence": 85,
        "reasoning": "The presence of deceivers and false teachings introduces a negative element, as it threatens the truth and faith of believers."
      },
      "emotions": {
        "Joy": {
          "weight": 0.1,
          "confidence": 60,
          "reasoning": "Recognizing and resisting deception brings a subtle joy."
        },
        "Trust": {
          "weight": 0.2,
          "confidence": 65,
          "reasoning": "It requires trust in true teachings."
        },
        "Fear": {
          "weight": 0.8,
          "confidence": 90,
          "reasoning": "The danger of being deceived evokes fear."
        },
        "Surprise": {
          "weight": 0.5,
          "confidence": 80,
          "reasoning": "The deceptive tactics might be surprising."
        },
        "Sadness": {
          "weight": 0.7,
          "confidence": 85,
          "reasoning": "Deception and false teachings are sources of sadness and spiritual loss."
        },
        "Disgust": {
          "weight": 0.8,
          "confidence": 90,
          "reasoning": "Deception is a morally disgusting practice."
        },
        "Anger": {
          "weight": 0.7,
          "confidence": 85,
          "reasoning": "Deceivers provoke anger and opposition."
        },
        "Anticipation": {
          "weight": 0.3,
          "confidence": 70,
          "reasoning": "There's anticipation of continued deception or exposure of the truth."
        }
      }
    }
  ]
}